README.rst
setup.py
taskwarrior_hook_time_tracking.egg-info/PKG-INFO
taskwarrior_hook_time_tracking.egg-info/SOURCES.txt
taskwarrior_hook_time_tracking.egg-info/dependency_links.txt
taskwarrior_hook_time_tracking.egg-info/entry_points.txt
taskwarrior_hook_time_tracking.egg-info/top_level.txt
time_tracking_hook/__init__.py