Metadata-Version: 1.1
Name: taskwarrior-hook-time-tracking
Version: 0.1.1
Summary: Track your time in a UDA in taskwarrior
Home-page: https://github.com/coddingtonbear/taskwarrior-hook-time-tracking
Author: Adam Coddington
Author-email: me@adamcoddington.net
License: UNKNOWN
Platform: UNKNOWN
Classifier: License :: OSI Approved :: MIT License
Classifier: Operating System :: OS Independent
